odoo/addons/pos_default_empty_image/README.rst
odoo/addons/pos_default_empty_image/__init__.py
odoo/addons/pos_default_empty_image/__manifest__.py
odoo/addons/pos_default_empty_image/i18n/es.po
odoo/addons/pos_default_empty_image/i18n/pos_default_empty_image.pot
odoo/addons/pos_default_empty_image/models/__init__.py
odoo/addons/pos_default_empty_image/models/pos_config.py
odoo/addons/pos_default_empty_image/models/product_product.py
odoo/addons/pos_default_empty_image/readme/CONFIGURATION.rst
odoo/addons/pos_default_empty_image/readme/CONTRIBUTORS.rst
odoo/addons/pos_default_empty_image/readme/DESCRIPTION.rst
odoo/addons/pos_default_empty_image/readme/HISTORY.rst
odoo/addons/pos_default_empty_image/static/description/icon.png
odoo/addons/pos_default_empty_image/static/description/index.html
odoo/addons/pos_default_empty_image/static/description/pos_config_form.png
odoo/addons/pos_default_empty_image/static/description/pos_display_default.png
odoo/addons/pos_default_empty_image/static/description/pos_display_improved.png
odoo/addons/pos_default_empty_image/static/src/css/pos_default_empty_image.css
odoo/addons/pos_default_empty_image/static/src/js/models.js
odoo/addons/pos_default_empty_image/static/src/js/widgets.js
odoo/addons/pos_default_empty_image/static/src/xml/pos_default_empty_image.xml
odoo/addons/pos_default_empty_image/views/pos_config.xml
odoo/addons/pos_default_empty_image/views/templates.xml
odoo12_addon_pos_default_empty_image-12.0.1.1.1.dist-info/METADATA
odoo12_addon_pos_default_empty_image-12.0.1.1.1.dist-info/WHEEL
odoo12_addon_pos_default_empty_image-12.0.1.1.1.dist-info/top_level.txt
odoo12_addon_pos_default_empty_image-12.0.1.1.1.dist-info/RECORD
